ismoiloff/__init__.py
ismoiloff/core.py
ismoiloffs-0.1.0.dist-info/METADATA
ismoiloffs-0.1.0.dist-info/WHEEL
ismoiloffs-0.1.0.dist-info/top_level.txt
ismoiloffs-0.1.0.dist-info/RECORD
