Metadata-Version: 2.4
Name: ismoiloffs
Version: 0.1.0
Summary: Run remote scripts securely using your Ismoiloff cloud executor.
Home-page: https://github.com/ismoiloff/ismoiloff
Author: ISMOILOFF
Author-email: ismoiloff <admin@ismoiloff.uz>
Project-URL: Home, https://github.com/yourusername/ismoiloff
Project-URL: Documentation, https://github.com/yourusername/ismoiloff
Requires-Python: >=3.10
Dynamic: author
Dynamic: home-page
Dynamic: requires-python
